nomad_sync_job_dispatch/__init__.py
nomad_sync_job_dispatch/_cli.py
nomad_sync_job_dispatch-0.2.4.dist-info/LICENSE
nomad_sync_job_dispatch-0.2.4.dist-info/METADATA
nomad_sync_job_dispatch-0.2.4.dist-info/WHEEL
nomad_sync_job_dispatch-0.2.4.dist-info/entry_points.txt
nomad_sync_job_dispatch-0.2.4.dist-info/top_level.txt
nomad_sync_job_dispatch-0.2.4.dist-info/RECORD
